leap_ec/__init__.py
leap_ec/__version__.py
leap_ec/algorithm.py
leap_ec/data.py
leap_ec/decoder.py
leap_ec/global_vars.py
leap_ec/individual.py
leap_ec/ops.py
leap_ec/parsimony.py
leap_ec/probe.py
leap_ec/problem.py
leap_ec/representation.py
leap_ec/simple.py
leap_ec/statistical_helpers.py
leap_ec/util.py
leap_ec/binary_rep/__init__.py
leap_ec/binary_rep/decoders.py
leap_ec/binary_rep/initializers.py
leap_ec/binary_rep/ops.py
leap_ec/binary_rep/problems.py
leap_ec/contrib/__init__.py
leap_ec/contrib/analysis.py
leap_ec/contrib/transfer/PopulationSeedingRepertoire_example.ipynb
leap_ec/contrib/transfer/__init__.py
leap_ec/contrib/transfer/sequential.py
leap_ec/distrib/README.md
leap_ec/distrib/__init__.py
leap_ec/distrib/asynchronous.py
leap_ec/distrib/evaluate.py
leap_ec/distrib/individual.py
leap_ec/distrib/logger.py
leap_ec/distrib/probe.py
leap_ec/distrib/synchronous.py
leap_ec/executable_rep/__init__.py
leap_ec/executable_rep/cgp.py
leap_ec/executable_rep/executable.py
leap_ec/executable_rep/neural_network.py
leap_ec/executable_rep/problems.py
leap_ec/executable_rep/rules.py
leap_ec/int_rep/__init__.py
leap_ec/int_rep/initializers.py
leap_ec/int_rep/ops.py
leap_ec/landscape_features/__init__.py
leap_ec/landscape_features/exploratory.py
leap_ec/multiobjective/README.md
leap_ec/multiobjective/__init__.py
leap_ec/multiobjective/asynchronous.py
leap_ec/multiobjective/nsga2.py
leap_ec/multiobjective/ops.py
leap_ec/multiobjective/probe.py
leap_ec/multiobjective/problems.py
leap_ec/real_rep/__init__.py
leap_ec/real_rep/initializers.py
leap_ec/real_rep/ops.py
leap_ec/real_rep/problems.py
leap_ec/segmented_rep/README.md
leap_ec/segmented_rep/__init__.py
leap_ec/segmented_rep/decoders.py
leap_ec/segmented_rep/initializers.py
leap_ec/segmented_rep/ops.py
leap_ec-0.8.2.dist-info/METADATA
leap_ec-0.8.2.dist-info/WHEEL
leap_ec-0.8.2.dist-info/licenses/LICENSE
leap_ec-0.8.2.dist-info/RECORD
