Metadata-Version: 2.4
Name: leap_ec
Version: 0.8.2
Summary: A general purpose Library for Evolutionary Algorithms in Python.
Author: Jeff Bassett
Author-email: Mark Coletti <mcoletti@gmail.com>, Eric Scott <escott@mitre.orgb>
License: Academic Free License (AFL)
License-File: LICENSE
Keywords: evolutionary algorithms,optimization,python
Classifier: License :: OSI Approved :: Academic Free License (AFL)
Classifier: Operating System :: OS Independent
Classifier: Programming Language :: Python :: 3
Requires-Python: >=3.11
Requires-Dist: dask==2024.6.2
Requires-Dist: distributed==2024.6.2
Requires-Dist: docopt~=0.6.2
Requires-Dist: matplotlib
Requires-Dist: networkx~=3.0
Requires-Dist: numpy~=2.0
Requires-Dist: omegaconf~=2.3.0
Requires-Dist: pandas
Requires-Dist: rich~=13.0.0
Requires-Dist: scipy
Requires-Dist: toolz~=0.12.0
Provides-Extra: development
Requires-Dist: click; extra == 'development'
Requires-Dist: coveralls; extra == 'development'
Requires-Dist: flake8; extra == 'development'
Requires-Dist: gymnasium; extra == 'development'
Requires-Dist: ipython; extra == 'development'
Requires-Dist: ipython-genutils; extra == 'development'
Requires-Dist: ipywidgets; extra == 'development'
Requires-Dist: jupyter; extra == 'development'
Requires-Dist: nbconvert; extra == 'development'
Requires-Dist: nbformat; extra == 'development'
Requires-Dist: pillow; extra == 'development'
Requires-Dist: pytest; extra == 'development'
Requires-Dist: pytest-cov; extra == 'development'
Requires-Dist: python-coveralls; extra == 'development'
Requires-Dist: seaborn; extra == 'development'
Requires-Dist: sphinx; extra == 'development'
Requires-Dist: sphinx-rtd-theme; extra == 'development'
Provides-Extra: documentation
Requires-Dist: sphinx; extra == 'documentation'
Requires-Dist: sphinx-rtd-theme; extra == 'documentation'
Requires-Dist: sphinxcontrib-applehelp; extra == 'documentation'
Requires-Dist: sphinxcontrib-bibtex; extra == 'documentation'
Requires-Dist: sphinxcontrib-devhelp; extra == 'documentation'
Requires-Dist: sphinxcontrib-htmlhelp; extra == 'documentation'
Requires-Dist: sphinxcontrib-jsmath; extra == 'documentation'
Requires-Dist: sphinxcontrib-qthelp; extra == 'documentation'
Requires-Dist: sphinxcontrib-serializinghtml; extra == 'documentation'
